redkeys/VERSION
redkeys/__init__.py
redkeys/api.py
redkeys/cli.py
redkeys/version.py
redkeys-0.0.5.dist-info/LICENSE
redkeys-0.0.5.dist-info/METADATA
redkeys-0.0.5.dist-info/WHEEL
redkeys-0.0.5.dist-info/entry_points.txt
redkeys-0.0.5.dist-info/top_level.txt
redkeys-0.0.5.dist-info/RECORD
