Metadata-Version: 2.1
Name: redkeys
Version: 0.0.5
Summary: Redis Keyspace Stats
Home-page: https://github.com/72squared/redkeys
Author: John Loehrer
Author-email: 72squared@gmail.com
License: MIT
Download-URL: https://github.com/72squared/redkeys/archive/0.0.5.tar.gz
Keywords: redis
Platform: UNKNOWN
Classifier: Development Status :: 4 - Beta
Classifier: Programming Language :: Python
Classifier: Programming Language :: Python
Classifier: Programming Language :: Python :: Implementation :: CPython
Classifier: Programming Language :: Python :: Implementation :: PyPy
Classifier: Programming Language :: Python :: 2
Classifier: Programming Language :: Python :: 2.7
Classifier: Programming Language :: Python :: 3
Classifier: Programming Language :: Python :: 3.3
Classifier: Programming Language :: Python :: 3.4
Classifier: Programming Language :: Python :: 3.5
Classifier: Environment :: Web Environment
Classifier: Operating System :: POSIX
Requires-Dist: redis (>=2.10.2)
